{
  "target_fecha": "2026-04-20",
  "target_hora": "5PM",
  "target_datetime": "2026-04-20 17:00:00",
  "top3": [
    "82",
    "62",
    "94"
  ],
  "top12": [
    "82",
    "62",
    "94",
    "52",
    "77",
    "86",
    "93",
    "98",
    "31",
    "06",
    "57",
    "71"
  ],
  "top_pairs": [],
  "pairs": [],
  "edge_label": "EDGE MODERADO",
  "fire": "🔥",
  "alert_level": "LOW",
  "strong_detected": "0",
  "risk_flag": "Riesgo: señal inestable",
  "best_score": 0.655069,
  "best_lift": 2.28265,
  "best_mi": 0.000456,
  "best_chi2": 6.839181,
  "active_edges": 7,
  "rows_used": 5593,
  "support": 1468,
  "context": {
    "lag1": [
      "60",
      "44",
      "40"
    ],
    "lag2": [
      "82",
      "19",
      "93"
    ],
    "lag3": [
      "41",
      "78",
      "09"
    ]
  },
  "last_draw": {
    "fecha": "2026-04-20",
    "hora": "4PM",
    "nums": [
      "60",
      "44",
      "40"
    ]
  },
  "last_3_draws": [
    {
      "fecha": "2026-04-20",
      "hora": "2PM",
      "nums": [
        "41",
        "78",
        "09"
      ]
    },
    {
      "fecha": "2026-04-20",
      "hora": "3PM",
      "nums": [
        "82",
        "19",
        "93"
      ]
    },
    {
      "fecha": "2026-04-20",
      "hora": "4PM",
      "nums": [
        "60",
        "44",
        "40"
      ]
    }
  ],
  "candidates": [
    {
      "num": "82",
      "score": 0.6550689861748246,
      "lift": 2.2826500140805592,
      "mi": 0.00045614827843688084,
      "chi2": 6.839180636885476,
      "active_edges": 7,
      "support": 1468
    },
    {
      "num": "62",
      "score": 0.5806089620698872,
      "lift": 2.4121620664797336,
      "mi": 0.0005108668262413226,
      "chi2": 7.833825963908232,
      "active_edges": 5,
      "support": 1468
    },
    {
      "num": "94",
      "score": 0.5630599681219032,
      "lift": 1.9826302133353766,
      "mi": 0.00044397355628088297,
      "chi2": 6.238552812901862,
      "active_edges": 7,
      "support": 1468
    },
    {
      "num": "52",
      "score": 0.5525534940448853,
      "lift": 2.0176767106824958,
      "mi": 0.0005020065112538753,
      "chi2": 7.139328168688795,
      "active_edges": 7,
      "support": 1468
    },
    {
      "num": "77",
      "score": 0.5274365719095154,
      "lift": 1.695490664076639,
      "mi": 0.0004278806428265943,
      "chi2": 3.2795237106152384,
      "active_edges": 7,
      "support": 1468
    },
    {
      "num": "86",
      "score": 0.5249651565436297,
      "lift": 1.9624560681402405,
      "mi": 0.00028184088406842263,
      "chi2": 3.984326368377067,
      "active_edges": 8,
      "support": 1468
    },
    {
      "num": "93",
      "score": 0.5170520483837892,
      "lift": 1.7518792979173703,
      "mi": 0.000875603829509498,
      "chi2": 5.043121091922834,
      "active_edges": 7,
      "support": 1468
    },
    {
      "num": "98",
      "score": 0.5104362382041489,
      "lift": 1.928620622237828,
      "mi": 0.0002689257225144728,
      "chi2": 3.776169125669119,
      "active_edges": 6,
      "support": 1468
    },
    {
      "num": "31",
      "score": 0.5097430446200834,
      "lift": 1.6413792452367841,
      "mi": 0.0006853675165740986,
      "chi2": 3.9331044840018405,
      "active_edges": 7,
      "support": 1468
    },
    {
      "num": "06",
      "score": 0.4959715069281796,
      "lift": 2.2485927938588492,
      "mi": 0.0005956917524959904,
      "chi2": 8.84734232261495,
      "active_edges": 7,
      "support": 1468
    },
    {
      "num": "57",
      "score": 0.49191865755664066,
      "lift": 2.46900415690121,
      "mi": 0.0008479157145502556,
      "chi2": 13.0561432051348,
      "active_edges": 4,
      "support": 1468
    },
    {
      "num": "71",
      "score": 0.4893873137474598,
      "lift": 1.9330644463765843,
      "mi": 0.00030586274904315016,
      "chi2": 4.295667691516448,
      "active_edges": 7,
      "support": 1468
    },
    {
      "num": "04",
      "score": 0.4851328314080281,
      "lift": 1.683624260336174,
      "mi": 0.0007195640095606501,
      "chi2": 4.131977091929317,
      "active_edges": 5,
      "support": 1468
    },
    {
      "num": "20",
      "score": 0.4813931855242618,
      "lift": 1.6661259864956652,
      "mi": 0.0008583487969900072,
      "chi2": 4.941918345381923,
      "active_edges": 7,
      "support": 1468
    },
    {
      "num": "56",
      "score": 0.4698268830444409,
      "lift": 2.0356687247489447,
      "mi": 0.0003907409302439021,
      "chi2": 5.593491131475096,
      "active_edges": 4,
      "support": 1468
    },
    {
      "num": "34",
      "score": 0.46901293420206525,
      "lift": 1.7843671812706932,
      "mi": 0.00024182473131847688,
      "chi2": 3.292736954116305,
      "active_edges": 6,
      "support": 1468
    },
    {
      "num": "24",
      "score": 0.45446974161474857,
      "lift": 2.337721968825185,
      "mi": 0.0005350388336818625,
      "chi2": 8.09045281766566,
      "active_edges": 6,
      "support": 1468
    },
    {
      "num": "33",
      "score": 0.45296944172735615,
      "lift": 1.7319363585259233,
      "mi": 0.00036364387305070885,
      "chi2": 2.95591831539579,
      "active_edges": 7,
      "support": 1468
    },
    {
      "num": "07",
      "score": 0.45274662684874806,
      "lift": 2.036376205716924,
      "mi": 0.00043163172067736937,
      "chi2": 6.170976871296818,
      "active_edges": 6,
      "support": 1468
    },
    {
      "num": "79",
      "score": 0.4477500907302369,
      "lift": 2.179888670216921,
      "mi": 0.000507752707085604,
      "chi2": 7.456188807452163,
      "active_edges": 6,
      "support": 1468
    }
  ],
  "signal_key": "2026-04-20|Anguilla|5PM",
  "fingerprint": "65b6189da331dc5ccc84dbb2bf78ab8e",
  "generated_rd": "2026-04-20 16:51:10",
  "workflow": {
    "notify_enabled": true,
    "notify_dedupe": true,
    "force_notify": false,
    "bootstrap_backfill": false,
    "bootstrap_days": 365,
    "min_ok_draws": 30
  }
}