{
  "target_fecha": "2026-04-16",
  "target_hora": "12PM",
  "target_datetime": "2026-04-16 12:00:00",
  "top3": [
    "70",
    "36",
    "07"
  ],
  "top12": [
    "70",
    "36",
    "07",
    "77",
    "27",
    "02",
    "91",
    "80",
    "39",
    "50",
    "01",
    "85"
  ],
  "top_pairs": [],
  "pairs": [],
  "edge_label": "NO JUGAR",
  "fire": "❌",
  "alert_level": "NONE",
  "strong_detected": "0",
  "risk_flag": "",
  "best_score": 0.805446,
  "best_lift": 2.046443,
  "best_mi": 0.000442,
  "best_chi2": 6.264886,
  "active_edges": 7,
  "rows_used": 5528,
  "support": 1523,
  "context": {
    "lag1": [
      "57",
      "76",
      "17"
    ],
    "lag2": [
      "50",
      "26",
      "83"
    ],
    "lag3": [
      "91",
      "00",
      "19"
    ]
  },
  "last_draw": {
    "fecha": "2026-04-16",
    "hora": "11AM",
    "nums": [
      "57",
      "76",
      "17"
    ]
  },
  "last_3_draws": [
    {
      "fecha": "2026-04-16",
      "hora": "9AM",
      "nums": [
        "91",
        "00",
        "19"
      ]
    },
    {
      "fecha": "2026-04-16",
      "hora": "10AM",
      "nums": [
        "50",
        "26",
        "83"
      ]
    },
    {
      "fecha": "2026-04-16",
      "hora": "11AM",
      "nums": [
        "57",
        "76",
        "17"
      ]
    }
  ],
  "candidates": [
    {
      "num": "70",
      "score": 0.8054462133561585,
      "lift": 2.0464426910576146,
      "mi": 0.0004424432559093133,
      "chi2": 6.264886454836515,
      "active_edges": 7,
      "support": 1523
    },
    {
      "num": "36",
      "score": 0.7360026839252168,
      "lift": 1.9847053495831308,
      "mi": 0.0003706181841095378,
      "chi2": 5.191923853461017,
      "active_edges": 7,
      "support": 1523
    },
    {
      "num": "07",
      "score": 0.6530243621152753,
      "lift": 2.667401853426596,
      "mi": 0.000988341143768583,
      "chi2": 15.529766139051478,
      "active_edges": 5,
      "support": 1523
    },
    {
      "num": "77",
      "score": 0.6446066535149199,
      "lift": 2.154185813465523,
      "mi": 0.0005479781662736879,
      "chi2": 7.911572448192748,
      "active_edges": 7,
      "support": 1523
    },
    {
      "num": "27",
      "score": 0.6039351735760319,
      "lift": 2.0683977438426604,
      "mi": 0.00041133091426521877,
      "chi2": 5.854202142651679,
      "active_edges": 8,
      "support": 1523
    },
    {
      "num": "02",
      "score": 0.5829712536265022,
      "lift": 2.9115167533396806,
      "mi": 0.0012295139756086089,
      "chi2": 20.02360003811661,
      "active_edges": 5,
      "support": 1523
    },
    {
      "num": "91",
      "score": 0.5760150295616673,
      "lift": 2.178522098671284,
      "mi": 0.0008382349269855133,
      "chi2": 8.145815559344873,
      "active_edges": 6,
      "support": 1523
    },
    {
      "num": "80",
      "score": 0.5745331983361066,
      "lift": 2.255559260214534,
      "mi": 0.0006072280391067985,
      "chi2": 8.928461753989627,
      "active_edges": 6,
      "support": 1523
    },
    {
      "num": "39",
      "score": 0.5609678268878284,
      "lift": 2.0739970484825103,
      "mi": 0.0005446114127750886,
      "chi2": 7.739869340223622,
      "active_edges": 5,
      "support": 1523
    },
    {
      "num": "50",
      "score": 0.5597797840432445,
      "lift": 2.0317417239786155,
      "mi": 0.0004346123323389678,
      "chi2": 6.138432827948839,
      "active_edges": 6,
      "support": 1523
    },
    {
      "num": "01",
      "score": 0.543377132913433,
      "lift": 2.4381715189152975,
      "mi": 0.0006508075324872056,
      "chi2": 9.882218985956758,
      "active_edges": 4,
      "support": 1523
    },
    {
      "num": "85",
      "score": 0.5215272539665281,
      "lift": 1.821266723101447,
      "mi": 0.00023076969947841836,
      "chi2": 3.1321066166461957,
      "active_edges": 5,
      "support": 1523
    },
    {
      "num": "37",
      "score": 0.517294861532679,
      "lift": 2.0252380692923846,
      "mi": 0.0003682334312690139,
      "chi2": 4.941332752212695,
      "active_edges": 6,
      "support": 1523
    },
    {
      "num": "08",
      "score": 0.49917881348587057,
      "lift": 2.1968207333483987,
      "mi": 0.0005232851933195447,
      "chi2": 7.621060210203442,
      "active_edges": 5,
      "support": 1523
    },
    {
      "num": "17",
      "score": 0.489587254843201,
      "lift": 1.8364227707045413,
      "mi": 0.0003717853417746818,
      "chi2": 4.058036168464972,
      "active_edges": 8,
      "support": 1523
    },
    {
      "num": "89",
      "score": 0.4870286858170607,
      "lift": 2.0801860289794507,
      "mi": 0.0004604703087468735,
      "chi2": 6.560291645911202,
      "active_edges": 7,
      "support": 1523
    },
    {
      "num": "61",
      "score": 0.4777594216318567,
      "lift": 2.147838674793501,
      "mi": 0.0003568842800809,
      "chi2": 5.164892115819716,
      "active_edges": 5,
      "support": 1523
    },
    {
      "num": "28",
      "score": 0.4769671466054266,
      "lift": 1.9075223641703027,
      "mi": 0.00031800095214641025,
      "chi2": 4.118577429691,
      "active_edges": 4,
      "support": 1523
    },
    {
      "num": "15",
      "score": 0.47311004084973907,
      "lift": 1.9847053495831308,
      "mi": 0.0003706181841095378,
      "chi2": 5.191923853461017,
      "active_edges": 5,
      "support": 1523
    },
    {
      "num": "38",
      "score": 0.4616482037643435,
      "lift": 1.9679600597388383,
      "mi": 0.0003246475421534938,
      "chi2": 4.5350413069492985,
      "active_edges": 5,
      "support": 1523
    }
  ],
  "signal_key": "2026-04-16|Anguilla|12PM",
  "fingerprint": "d2dbe5ec51b37a76d460f3e649ec4aaf",
  "generated_rd": "2026-04-16 11:40:11",
  "workflow": {
    "notify_enabled": true,
    "notify_dedupe": true,
    "force_notify": false,
    "bootstrap_backfill": false,
    "bootstrap_days": 365,
    "min_ok_draws": 30
  }
}