{
  "target_fecha": "2026-04-07",
  "target_hora": "10AM",
  "target_datetime": "2026-04-07 10:00:00",
  "top3": [
    "38",
    "85",
    "80"
  ],
  "top12": [
    "38",
    "85",
    "80",
    "09",
    "75",
    "33",
    "60",
    "04",
    "95",
    "25",
    "36",
    "87"
  ],
  "top_pairs": [],
  "pairs": [],
  "edge_label": "EDGE REAL",
  "fire": "🔥🔥🔥",
  "alert_level": "MEDIUM",
  "strong_detected": "0",
  "risk_flag": "Riesgo: alta densidad de edges",
  "best_score": 0.862708,
  "best_lift": 2.550142,
  "best_mi": 0.000659,
  "best_chi2": 9.944518,
  "active_edges": 8,
  "rows_used": 5391,
  "support": 1396,
  "context": {
    "lag1": [
      "11",
      "17",
      "18"
    ],
    "lag2": [
      "89",
      "61",
      "94"
    ],
    "lag3": [
      "62",
      "49",
      "59"
    ]
  },
  "last_draw": {
    "fecha": "2026-04-07",
    "hora": "9AM",
    "nums": [
      "11",
      "17",
      "18"
    ]
  },
  "last_3_draws": [
    {
      "fecha": "2026-04-06",
      "hora": "10PM",
      "nums": [
        "62",
        "49",
        "59"
      ]
    },
    {
      "fecha": "2026-04-07",
      "hora": "8AM",
      "nums": [
        "89",
        "61",
        "94"
      ]
    },
    {
      "fecha": "2026-04-07",
      "hora": "9AM",
      "nums": [
        "11",
        "17",
        "18"
      ]
    }
  ],
  "candidates": [
    {
      "num": "38",
      "score": 0.862707886294533,
      "lift": 2.550141820023934,
      "mi": 0.0006586136927010263,
      "chi2": 9.944518096967276,
      "active_edges": 8,
      "support": 1396
    },
    {
      "num": "85",
      "score": 0.7843947808187465,
      "lift": 2.817595726195462,
      "mi": 0.0009478743559318678,
      "chi2": 14.887170491942934,
      "active_edges": 7,
      "support": 1396
    },
    {
      "num": "80",
      "score": 0.7059552455122045,
      "lift": 2.265363935695253,
      "mi": 0.0006292013944433461,
      "chi2": 9.035173220503232,
      "active_edges": 5,
      "support": 1396
    },
    {
      "num": "09",
      "score": 0.6234929514532834,
      "lift": 1.8129539369809882,
      "mi": 0.00029453116019423906,
      "chi2": 3.8854887798757303,
      "active_edges": 6,
      "support": 1396
    },
    {
      "num": "75",
      "score": 0.5967102594582803,
      "lift": 3.0457626190977045,
      "mi": 0.0012599072605716435,
      "chi2": 20.406059062359237,
      "active_edges": 7,
      "support": 1396
    },
    {
      "num": "33",
      "score": 0.5959445681529527,
      "lift": 2.040327939658783,
      "mi": 0.0008021808632072484,
      "chi2": 5.44817117805126,
      "active_edges": 6,
      "support": 1396
    },
    {
      "num": "60",
      "score": 0.593140197993441,
      "lift": 1.7916250678105292,
      "mi": 0.00028396150374583855,
      "chi2": 3.7294793435774,
      "active_edges": 6,
      "support": 1396
    },
    {
      "num": "04",
      "score": 0.5891473510332784,
      "lift": 2.2164661502231615,
      "mi": 0.0004034398668527608,
      "chi2": 5.662486549736621,
      "active_edges": 5,
      "support": 1396
    },
    {
      "num": "95",
      "score": 0.5883076117374795,
      "lift": 2.2447534180533157,
      "mi": 0.000509912541707969,
      "chi2": 7.306704422834509,
      "active_edges": 6,
      "support": 1396
    },
    {
      "num": "25",
      "score": 0.5404781582663767,
      "lift": 2.2187213417559906,
      "mi": 0.0004954672307396094,
      "chi2": 7.062696642267425,
      "active_edges": 4,
      "support": 1396
    },
    {
      "num": "36",
      "score": 0.5271746521200527,
      "lift": 1.9953363742903698,
      "mi": 0.0004279058499096737,
      "chi2": 5.279632446317031,
      "active_edges": 7,
      "support": 1396
    },
    {
      "num": "87",
      "score": 0.4846677972721363,
      "lift": 1.844653490494706,
      "mi": 0.000370735041001608,
      "chi2": 3.27410384688434,
      "active_edges": 5,
      "support": 1396
    },
    {
      "num": "69",
      "score": 0.48331027221254136,
      "lift": 2.0932669938874433,
      "mi": 0.0004347537991192525,
      "chi2": 6.062576127707459,
      "active_edges": 6,
      "support": 1396
    },
    {
      "num": "15",
      "score": 0.44210458701523275,
      "lift": 2.0080455227347986,
      "mi": 0.00039212378328269963,
      "chi2": 5.380044103124064,
      "active_edges": 5,
      "support": 1396
    },
    {
      "num": "22",
      "score": 0.4388965761350932,
      "lift": 1.7969999354158226,
      "mi": 0.00019796291420534097,
      "chi2": 2.6097102851877376,
      "active_edges": 6,
      "support": 1396
    },
    {
      "num": "17",
      "score": 0.43773827459134784,
      "lift": 1.8329252791478876,
      "mi": 0.00030455138503883135,
      "chi2": 4.0353338405584385,
      "active_edges": 6,
      "support": 1396
    },
    {
      "num": "82",
      "score": 0.4309789828770907,
      "lift": 2.0671011496067657,
      "mi": 0.0003779778815822739,
      "chi2": 5.249973998999551,
      "active_edges": 3,
      "support": 1396
    },
    {
      "num": "76",
      "score": 0.4238924510374583,
      "lift": 1.750438285918551,
      "mi": 0.0002686254935600783,
      "chi2": 3.5051149367859837,
      "active_edges": 7,
      "support": 1396
    },
    {
      "num": "20",
      "score": 0.41711587670188555,
      "lift": 1.837423252113198,
      "mi": 0.00027484855658872526,
      "chi2": 3.647301547899297,
      "active_edges": 7,
      "support": 1396
    },
    {
      "num": "51",
      "score": 0.41612380347304395,
      "lift": 1.8238099482292291,
      "mi": 0.0003843519507196095,
      "chi2": 3.9654920999594916,
      "active_edges": 5,
      "support": 1396
    }
  ],
  "signal_key": "2026-04-07|Anguilla|10AM",
  "fingerprint": "39dbd1307a4f2ce227844aceef70d960",
  "generated_rd": "2026-04-07 09:20:42",
  "workflow": {
    "notify_enabled": true,
    "notify_dedupe": true,
    "force_notify": false,
    "bootstrap_backfill": false,
    "bootstrap_days": 365,
    "min_ok_draws": 30
  }
}