{
  "target_fecha": "2026-04-06",
  "target_hora": "4PM",
  "target_datetime": "2026-04-06 16:00:00",
  "top3": [
    "62",
    "44",
    "21"
  ],
  "top12": [
    "62",
    "44",
    "21",
    "02",
    "09",
    "75",
    "93",
    "01",
    "49",
    "36",
    "19",
    "55"
  ],
  "top_pairs": [],
  "pairs": [],
  "edge_label": "EDGE REAL",
  "fire": "🔥🔥🔥",
  "alert_level": "MEDIUM",
  "strong_detected": "0",
  "risk_flag": "",
  "best_score": 0.726684,
  "best_lift": 2.562044,
  "best_mi": 0.000596,
  "best_chi2": 9.015337,
  "active_edges": 5,
  "rows_used": 5382,
  "support": 1404,
  "context": {
    "lag1": [
      "39",
      "81",
      "68"
    ],
    "lag2": [
      "72",
      "03",
      "27"
    ],
    "lag3": [
      "31",
      "43",
      "80"
    ]
  },
  "last_draw": {
    "fecha": "2026-04-06",
    "hora": "3PM",
    "nums": [
      "39",
      "81",
      "68"
    ]
  },
  "last_3_draws": [
    {
      "fecha": "2026-04-06",
      "hora": "1PM",
      "nums": [
        "31",
        "43",
        "80"
      ]
    },
    {
      "fecha": "2026-04-06",
      "hora": "2PM",
      "nums": [
        "72",
        "03",
        "27"
      ]
    },
    {
      "fecha": "2026-04-06",
      "hora": "3PM",
      "nums": [
        "39",
        "81",
        "68"
      ]
    }
  ],
  "candidates": [
    {
      "num": "62",
      "score": 0.7266837645021575,
      "lift": 2.562043694971393,
      "mi": 0.0005963229088084619,
      "chi2": 9.015336724919274,
      "active_edges": 5,
      "support": 1404
    },
    {
      "num": "44",
      "score": 0.701464655676676,
      "lift": 2.0011153828945716,
      "mi": 0.00039756364941144094,
      "chi2": 5.32523225959167,
      "active_edges": 6,
      "support": 1404
    },
    {
      "num": "21",
      "score": 0.6442803611555644,
      "lift": 1.9649506482316494,
      "mi": 0.0003711483434360185,
      "chi2": 5.041324939434568,
      "active_edges": 6,
      "support": 1404
    },
    {
      "num": "02",
      "score": 0.5767939052439433,
      "lift": 2.110404247338465,
      "mi": 0.0004104359737940581,
      "chi2": 5.663898276174253,
      "active_edges": 5,
      "support": 1404
    },
    {
      "num": "09",
      "score": 0.5750171703150605,
      "lift": 2.6685227409576133,
      "mi": 0.000941221029476689,
      "chi2": 14.411562668865212,
      "active_edges": 5,
      "support": 1404
    },
    {
      "num": "75",
      "score": 0.5727705392115312,
      "lift": 1.8317336588219717,
      "mi": 0.0003042801578319493,
      "chi2": 4.021855902400444,
      "active_edges": 6,
      "support": 1404
    },
    {
      "num": "93",
      "score": 0.550334910604704,
      "lift": 1.9970314667728775,
      "mi": 0.00034711471388386244,
      "chi2": 4.748839018207536,
      "active_edges": 5,
      "support": 1404
    },
    {
      "num": "01",
      "score": 0.5498785152014202,
      "lift": 2.067349473501137,
      "mi": 0.00037877331527845655,
      "chi2": 5.252305699628749,
      "active_edges": 5,
      "support": 1404
    },
    {
      "num": "49",
      "score": 0.5406351374018046,
      "lift": 2.2127658729850643,
      "mi": 0.0003925747156644674,
      "chi2": 5.5961616351716525,
      "active_edges": 6,
      "support": 1404
    },
    {
      "num": "36",
      "score": 0.539720317004683,
      "lift": 1.7928047357333021,
      "mi": 0.00019683554522638771,
      "chi2": 2.5874101672509697,
      "active_edges": 8,
      "support": 1404
    },
    {
      "num": "19",
      "score": 0.5396229353115817,
      "lift": 2.3289878472925043,
      "mi": 0.00043816650764040576,
      "chi2": 6.376782476779308,
      "active_edges": 8,
      "support": 1404
    },
    {
      "num": "55",
      "score": 0.5068259196962395,
      "lift": 2.0013386215967595,
      "mi": 0.0004958417195090434,
      "chi2": 5.321203383396657,
      "active_edges": 6,
      "support": 1404
    },
    {
      "num": "38",
      "score": 0.48513293490070186,
      "lift": 2.2995085700374687,
      "mi": 0.0007130117082089286,
      "chi2": 7.7727193882463155,
      "active_edges": 4,
      "support": 1404
    },
    {
      "num": "68",
      "score": 0.47674640096470583,
      "lift": 1.6871472832379866,
      "mi": 0.0002132991542310442,
      "chi2": 2.7436701311046976,
      "active_edges": 8,
      "support": 1404
    },
    {
      "num": "45",
      "score": 0.4742318963487562,
      "lift": 2.9999998965000034,
      "mi": 0.0010490644293216314,
      "chi2": 16.89291069253474,
      "active_edges": 5,
      "support": 1404
    },
    {
      "num": "73",
      "score": 0.465043192493208,
      "lift": 1.937888133976932,
      "mi": 0.0007609650934469854,
      "chi2": 4.207718721099008,
      "active_edges": 7,
      "support": 1404
    },
    {
      "num": "41",
      "score": 0.45050889760968826,
      "lift": 1.6293660804481938,
      "mi": 0.00017161020698006426,
      "chi2": 2.1604706118009536,
      "active_edges": 8,
      "support": 1404
    },
    {
      "num": "79",
      "score": 0.4483557210916501,
      "lift": 1.8233765624237497,
      "mi": 0.000888390140971062,
      "chi2": 4.923412888681492,
      "active_edges": 6,
      "support": 1404
    },
    {
      "num": "48",
      "score": 0.44804110235471434,
      "lift": 1.9815175555270126,
      "mi": 0.00037950028749257625,
      "chi2": 5.1713618392166865,
      "active_edges": 5,
      "support": 1404
    },
    {
      "num": "32",
      "score": 0.43685603355408237,
      "lift": 1.8918137103014663,
      "mi": 0.0003343449189244618,
      "chi2": 4.017492138819688,
      "active_edges": 7,
      "support": 1404
    }
  ],
  "signal_key": "2026-04-06|Anguilla|4PM",
  "fingerprint": "f13838da0cad4dfca1ec371c2b113214",
  "generated_rd": "2026-04-06 15:56:50",
  "workflow": {
    "notify_enabled": true,
    "notify_dedupe": true,
    "force_notify": false,
    "bootstrap_backfill": false,
    "bootstrap_days": 365,
    "min_ok_draws": 30
  }
}